znake/__init__.py
znake/__main__.py
znake/baseline.py
znake/builddir.py
znake/deb.py
znake/debtest.py
znake/doc.py
znake/docker.py
znake/format.py
znake/pypi.py
znake/setupgen.py
znake/static.py
znake/systest.py
znake/test.py
znake/tools.py
znake/util.py
znake/venv.py
znake/version.py
znake/data/flake8_config
znake/data/yapf_style
znake/data/znake.yaml
znake-1.1.0.post0.dist-info/LICENSE
znake-1.1.0.post0.dist-info/METADATA
znake-1.1.0.post0.dist-info/NOTICE
znake-1.1.0.post0.dist-info/WHEEL
znake-1.1.0.post0.dist-info/entry_points.txt
znake-1.1.0.post0.dist-info/top_level.txt
znake-1.1.0.post0.dist-info/RECORD
